byted_overpass_bytedance_videoarch_imagex_url/__init__.py
byted_overpass_bytedance_videoarch_imagex_url-0.0.1.dist-info/METADATA
byted_overpass_bytedance_videoarch_imagex_url-0.0.1.dist-info/WHEEL
byted_overpass_bytedance_videoarch_imagex_url-0.0.1.dist-info/top_level.txt
byted_overpass_bytedance_videoarch_imagex_url-0.0.1.dist-info/RECORD
